pygamma-4.3.4.data/purelib/pygamma/__init__.py
pygamma-4.3.4.data/purelib/pygamma/_pygamma.so
pygamma-4.3.4.data/purelib/pygamma/build_notes.txt
pygamma-4.3.4.data/purelib/pygamma/pygamma.py
pygamma-4.3.4.data/purelib/pygamma/pygamma_version.py
pygamma-4.3.4.dist-info/METADATA
pygamma-4.3.4.dist-info/WHEEL
pygamma-4.3.4.dist-info/top_level.txt
pygamma-4.3.4.dist-info/RECORD
